copra/__init__.py
copra/rest/__init__.py
copra/rest/client.py
copra/websocket/__init__.py
copra/websocket/channel.py
copra/websocket/client.py
copra-1.2.9.dist-info/AUTHORS.rst
copra-1.2.9.dist-info/LICENSE
copra-1.2.9.dist-info/METADATA
copra-1.2.9.dist-info/WHEEL
copra-1.2.9.dist-info/top_level.txt
copra-1.2.9.dist-info/RECORD
