Metadata-Version: 2.1
Name: copra
Version: 1.2.9
Summary: Asyncronous Python REST and WebSocket Clients for the Coinbase Pro virtual currency trading platform.
Home-page: https://github.com/tpodlaski/copra
Author: Tony Podlaski
Author-email: tony@podlaski.com
License: MIT license
Keywords: copra coinbase pro gdax api bitcoin litecoin etherium rest websocket client
Platform: UNKNOWN
Classifier: Development Status :: 5 - Production/Stable
Classifier: Intended Audience :: Developers
Classifier: License :: OSI Approved :: MIT License
Classifier: Natural Language :: English
Classifier: Programming Language :: Python :: 3
Classifier: Programming Language :: Python :: 3.5
Classifier: Programming Language :: Python :: 3.6
Requires-Dist: autobahn (>=18.8.1)
Requires-Dist: aiohttp (>=3.4.4)
Requires-Dist: python-dateutil
Requires-Dist: python-dotenv
Requires-Dist: asynctest
